pyb_utils/__init__.py
pyb_utils/bodies.py
pyb_utils/camera.py
pyb_utils/collision.py
pyb_utils/contact.py
pyb_utils/frame.py
pyb_utils/ghost.py
pyb_utils/math.py
pyb_utils/named_tuples.py
pyb_utils/robots.py
pyb_utils/utils.py
pyb_utils/version.py
pyb_utils/cli/pybview.py
pyb_utils-2.4.2.dist-info/METADATA
pyb_utils-2.4.2.dist-info/WHEEL
pyb_utils-2.4.2.dist-info/entry_points.txt
pyb_utils-2.4.2.dist-info/licenses/LICENSE
pyb_utils-2.4.2.dist-info/RECORD
