Metadata-Version: 2.4
Name: pyb_utils
Version: 2.4.2
Summary: Basic utilities for PyBullet, including collision detection, ghost (i.e. visual-only) objects, and cameras.
Author-email: Adam Heins <mail@adamheins.com>
License: MIT
License-File: LICENSE
Requires-Python: >=3.8
Requires-Dist: colorama>=0.4.6
Requires-Dist: matplotlib>=3.5.1
Requires-Dist: numpy>=1.24.0
Requires-Dist: opencv-python>=4.5.5
Requires-Dist: pillow>=10.0.1
Requires-Dist: pybullet>=3.2.1
Requires-Dist: scipy>=1.10.0
